beekeeper/core/__init__.py
beekeeper/core/schema.py
beekeeper/core/document/__init__.py
beekeeper/core/document/base.py
beekeeper/core/embeddings/__init__.py
beekeeper/core/embeddings/base.py
beekeeper/core/evaluation/__init__.py
beekeeper/core/evaluation/context_similarity.py
beekeeper/core/flows/__init__.py
beekeeper/core/flows/ingestion_flow.py
beekeeper/core/guardrails/__init__.py
beekeeper/core/guardrails/base.py
beekeeper/core/guardrails/types.py
beekeeper/core/llms/__init__.py
beekeeper/core/llms/base.py
beekeeper/core/llms/decorators.py
beekeeper/core/llms/types.py
beekeeper/core/monitors/__init__.py
beekeeper/core/monitors/base.py
beekeeper/core/monitors/types.py
beekeeper/core/observers/__init__.py
beekeeper/core/observers/base.py
beekeeper/core/observers/types.py
beekeeper/core/prompts/__init__.py
beekeeper/core/prompts/base.py
beekeeper/core/prompts/utils.py
beekeeper/core/readers/__init__.py
beekeeper/core/readers/base.py
beekeeper/core/readers/directory.py
beekeeper/core/text_chunkers/__init__.py
beekeeper/core/text_chunkers/base.py
beekeeper/core/text_chunkers/semantic.py
beekeeper/core/text_chunkers/sentence.py
beekeeper/core/text_chunkers/token.py
beekeeper/core/text_chunkers/utils.py
beekeeper/core/tools/__init__.py
beekeeper/core/tools/base.py
beekeeper/core/utils/pairwise.py
beekeeper/core/vector_stores/__init__.py
beekeeper/core/vector_stores/base.py
beekeeper_core-1.0.11.dist-info/METADATA
beekeeper_core-1.0.11.dist-info/WHEEL
beekeeper_core-1.0.11.dist-info/RECORD
